Metadata-Version: 2.1
Name: python-packaging-jg
Version: 0.1.4
Summary: Example of how to package Python code for release
Home-page: https://github.com/JaderGiacon/python-packaging-jg
Author: Jader Giacon
License: MIT
Platform: UNKNOWN
Requires-Python: >=3.7
License-File: LICENSE
Requires-Dist: numpy (>=1.22.2)
Requires-Dist: pandas
Requires-Dist: fire
Provides-Extra: dev
Requires-Dist: bump2version ; extra == 'dev'
Requires-Dist: pytest ; extra == 'dev'
Requires-Dist: flake8 ; extra == 'dev'
Requires-Dist: black ; extra == 'dev'
Requires-Dist: mypy ; extra == 'dev'
Requires-Dist: pre-commit ; extra == 'dev'
